<?xml version="1.0" encoding="UTF-8"?>
<objects serializationModel="Studio.01.10.00">
    <object class="AudioFile" id="{e7c5a9de-9df7-4164-9a53-080ed9d8cd45}">
        <property name="assetPath">
            <value>sfx_arg_04.wav</value>
        </property>
        <property name="frequencyInKHz">
            <value>44.0999985</value>
        </property>
        <property name="channelCount">
            <value>1</value>
        </property>
        <property name="length">
            <value>1.4044217687074829</value>
        </property>
        <relationship name="masterAssetFolder">
            <destination>{2e1d5e4e-e3e7-4820-b3d7-bf3799489769}</destination>
        </relationship>
    </object>
</objects>
